{
  "openapi": "3.0.1",
  "info": {
    "title": "JobPostingAPI",
    "version": "1.0"
  },
  "paths": {
    "/api/Jobs": {
      "get": {
        "tags": [
          "Jobs"
        ],
        "parameters": [
          {
            "name": "type",
            "in": "query",
            "schema": {
              "type": "string"
            }
          },
          {
            "name": "location",
            "in": "query",
            "schema": {
              "type": "string"
            }
          }
        ],
        "responses": {
          "200": {
            "description": "OK"
          }
        }
      },
      "post": {
        "tags": [
          "Jobs"
        ],
        "requestBody": {
          "content": {
            "application/json": {
              "schema": {
                "$ref": "#/components/schemas/Job"
              }
            },
            "text/json": {
              "schema": {
                "$ref": "#/components/schemas/Job"
              }
            },
            "application/*+json": {
              "schema": {
                "$ref": "#/components/schemas/Job"
              }
            }
          }
        },
        "responses": {
          "200": {
            "description": "OK"
          }
        }
      }
    },
    "/api/Jobs/{id}": {
      "delete": {
        "tags": [
          "Jobs"
        ],
        "parameters": [
          {
            "name": "id",
            "in": "path",
            "required": true,
            "schema": {
              "type": "integer",
              "format": "int32"
            }
          }
        ],
        "responses": {
          "200": {
            "description": "OK"
          }
        }
      }
    }
  },
  "components": {
    "schemas": {
      "Job": {
        "type": "object",
        "properties": {
          "id": {
            "type": "integer",
            "format": "int32"
          },
          "title": {
            "type": "string",
            "nullable": true
          },
          "description": {
            "type": "string",
            "nullable": true
          },
          "location": {
            "type": "string",
            "nullable": true
          },
          "type": {
            "type": "string",
            "nullable": true
          },
          "closingDate": {
            "type": "string",
            "format": "date-time"
          }
        },
        "additionalProperties": false
      }
    }
  }
}